normal_modes_tools/__init__.py
normal_modes_tools/__main__.py
normal_modes_tools/atomic_masses.py
normal_modes_tools/conversions.py
normal_modes_tools/decomposition.py
normal_modes_tools/franck_condon_factors.py
normal_modes_tools/geometry.py
normal_modes_tools/huang_rhys_factors.py
normal_modes_tools/normal_mode.py
normal_modes_tools/printing.py
normal_modes_tools/scan_result.py
normal_modes_tools/compare/__init__.py
normal_modes_tools/mulliken/__init__.py
normal_modes_tools/mulliken/core.py
normal_modes_tools-1.0.6.dist-info/METADATA
normal_modes_tools-1.0.6.dist-info/WHEEL
normal_modes_tools-1.0.6.dist-info/RECORD
