Metadata-Version: 2.4
Name: normal_modes_tools
Version: 1.0.6
Summary: Tools for working with normal modes
Project-URL: Homepage, https://github.com/the-pawel-wojcik/normal-modes-tools
Project-URL: Repository, https://github.com/the-pawel-wojcik/normal-modes-tools.git
Project-URL: Issues, https://github.com/the-pawel-wojcik/normal-modes-tools/issues
Author-email: Paweł Wójcik <pawel.wojcik5@gmail.com>
Keywords: chemistry
Requires-Python: >=3.13
Requires-Dist: matplotlib
Requires-Dist: numpy
Requires-Dist: xyz-parser
